README.md
pyhgf-0.2.8.dist-info/METADATA
pyhgf-0.2.8.dist-info/WHEEL
pyhgf-0.2.8.dist-info/licenses/LICENSE
pyhgf.libs/libgcc_s-27e5a392.so.1
pyhgf/__init__.py
pyhgf/data/binary_input.txt
pyhgf/data/binary_response.txt
pyhgf/data/usdchf.txt
pyhgf/distribution.py
pyhgf/math.py
pyhgf/model/__init__.py
pyhgf/model/add_nodes.py
pyhgf/model/hgf.py
pyhgf/model/network.py
pyhgf/plots/__init__.py
pyhgf/plots/graphviz/__init__.py
pyhgf/plots/graphviz/plot_network.py
pyhgf/plots/matplotlib/__init__.py
pyhgf/plots/matplotlib/plot_correlations.py
pyhgf/plots/matplotlib/plot_nodes.py
pyhgf/plots/matplotlib/plot_samples.py
pyhgf/plots/matplotlib/plot_trajectories.py
pyhgf/plots/networkx/__init__.py
pyhgf/plots/networkx/plot_network.py
pyhgf/response.py
pyhgf/rshgf.abi3.so
pyhgf/typing.py
pyhgf/updates/__init__.py
pyhgf/updates/learning.py
pyhgf/updates/observation.py
pyhgf/updates/posterior/__init__.py
pyhgf/updates/posterior/categorical.py
pyhgf/updates/posterior/continuous/__init__.py
pyhgf/updates/posterior/continuous/continuous_node_posterior_update.py
pyhgf/updates/posterior/continuous/continuous_node_posterior_update_ehgf.py
pyhgf/updates/posterior/continuous/continuous_node_posterior_update_unbounded.py
pyhgf/updates/posterior/continuous/posterior_update_mean_continuous_node.py
pyhgf/updates/posterior/continuous/posterior_update_precision_continuous_node.py
pyhgf/updates/posterior/exponential.py
pyhgf/updates/prediction/__init__.py
pyhgf/updates/prediction/binary.py
pyhgf/updates/prediction/continuous.py
pyhgf/updates/prediction/dirichlet.py
pyhgf/updates/prediction_error/__init__.py
pyhgf/updates/prediction_error/binary.py
pyhgf/updates/prediction_error/categorical.py
pyhgf/updates/prediction_error/continuous.py
pyhgf/updates/prediction_error/dirichlet.py
pyhgf/updates/prediction_error/exponential.py
pyhgf/utils/__init__.py
pyhgf/utils/add_edges.py
pyhgf/utils/add_parent.py
pyhgf/utils/beliefs_propagation.py
pyhgf/utils/fill_categorical_state_node.py
pyhgf/utils/get_input_idxs.py
pyhgf/utils/get_update_sequence.py
pyhgf/utils/learning.py
pyhgf/utils/list_branches.py
pyhgf-0.2.8.dist-info/RECORD
