Metadata-Version: 2.4
Name: pyhgf
Version: 0.2.8
Classifier: Programming Language :: Rust
Classifier: Programming Language :: Python :: Implementation :: CPython
Classifier: Programming Language :: Python :: Implementation :: PyPy
Requires-Dist: numpy>=2.0.0
Requires-Dist: matplotlib>=3.4.0
Requires-Dist: seaborn>=0.13.2
Requires-Dist: arviz>=0.21.0
Requires-Dist: pymc>=5.25.1
Requires-Dist: jax>=0.4.26,<0.4.32
Requires-Dist: jaxlib>=0.4.26,<0.4.32
Requires-Dist: graphviz>=0.20.3
License-File: LICENSE
Summary: Dynamic neural networks for predictive coding
Keywords: reinforcement learning,predictive coding,neural networks,graphs,variational inference,active inference,causal inference
Author-email: Nicolas Legrand <nicolas.legrand@cas.au.dk>
License-Expression: GPL-3.0
Requires-Python: >=3.10, <=3.13
Project-URL: homepage, https://computationalpsychiatry.github.io/pyhgf/
Project-URL: repository, https://github.com/ComputationalPsychiatry/pyhgf
Project-URL: documentation, https://computationalpsychiatry.github.io/pyhgf/learn.html
